{
  "format": "custom",
  "id": "horizontal_scroll_card_b",
  "label": "Horizontal Scroll Card B",
  "repeatable": false,
  "status": true,
  "json": {
    "Main": {
      "title": {
        "type": "Text",
        "config": {
          "label": "Title",
          "placeholder": ""
        }
      },
      "subtitle": {
        "type": "Text",
        "config": {
          "label": "subtitle",
          "placeholder": ""
        }
      },
      "year_data": {
        "type": "Group",
        "config": {
          "label": "year_data",
          "repeat": true,
          "fields": {
            "year": {
              "type": "Text",
              "config": {
                "label": "year",
                "placeholder": ""
              }
            },
            "data": {
              "type": "Text",
              "config": {
                "label": "data",
                "placeholder": ""
              }
            },
            "description": {
              "type": "Text",
              "config": {
                "label": "description",
                "placeholder": ""
              }
            }
          }
        }
      },
      "cirlce": {
        "type": "Image",
        "config": {
          "label": "cirlce",
          "constraint": {},
          "thumbnails": []
        }
      }
    }
  }
}
